jupyter_tool/__init__.py
jupyter_tool/jupyter.py
jupyter_tool-0.1.1.dist-info/METADATA
jupyter_tool-0.1.1.dist-info/WHEEL
jupyter_tool-0.1.1.dist-info/top_level.txt
jupyter_tool-0.1.1.dist-info/RECORD
